Metadata-Version: 2.1
Name: cpcat
Version: 0.1
Summary: A portable, scalable, and fast AI Data Lakehouse.
Home-page: https://github.com/ray-project/deltacat
Author: Patina Software Foundation
License: UNKNOWN
Platform: UNKNOWN
Classifier: Development Status :: 4 - Beta
Classifier: Intended Audience :: Developers
Classifier: Programming Language :: Python :: 3 :: Only
Classifier: Programming Language :: Python :: 3.10
Classifier: Programming Language :: Python :: 3.9
Classifier: Operating System :: OS Independent
Requires-Python: >=3.9
License-File: LICENSE
Requires-Dist: aws-embedded-metrics ==3.2.0
Requires-Dist: boto3 ~=1.34
Requires-Dist: getdaft ==0.3.6
Requires-Dist: intervaltree ==3.1.0
Requires-Dist: numpy ==1.21.5
Requires-Dist: pandas ==1.3.5
Requires-Dist: pyarrow ==17.0.0
Requires-Dist: pydantic ==1.10.4
Requires-Dist: pymemcache ==4.0.0
Requires-Dist: ray >=2.20.0
Requires-Dist: s3fs ==2024.5.0
Requires-Dist: tenacity ==8.2.3
Requires-Dist: typing-extensions ==4.6.1
Requires-Dist: redis ==4.6.0
Requires-Dist: schedule ==1.2.0
Provides-Extra: iceberg
Requires-Dist: pyiceberg[glue] >=0.6.0 ; extra == 'iceberg'
